{
  "event": {
    "name": "MWC BCN 2026",
    "startDate": "2026-03-02T00:00:00.000Z",
    "endDate": "2026-03-05T00:00:00.000Z",
    "geminiApiKey": "AIzaSyD3l8j-JEukPjNFhVZcV2HlWMLpMn2o734",
    "tags": [
      "APAC",
      "Americas",
      "Cloud",
      "Europe",
      "Global",
      "IS",
      "Japan Enterprise",
      "LATAM",
      "MEA",
      "OSS",
      "Open RAN MoU",
      "Partner",
      "RAN",
      "RMI"
    ],
    "meetingTypes": [
      "Channel Partner",
      "Govt",
      "Other",
      "PR Engagement",
      "Sales/Customer",
      "Technology Partner",
      "Vendor Partner"
    ],
    "attendeeTypes": [
      "BU Cloud",
      "BU IS",
      "BU OSS",
      "BU RAN",
      "Customer",
      "Customer Success",
      "Marketing",
      "Partner",
      "Press / Analyst",
      "Sales",
      "Staff",
      "Vendor"
    ],
    "timezone": "CET"
  },
  "attendees": [
    {
      "name": "Google Exec",
      "title": "Googlge",
      "email": "xxx@google.com",
      "bio": "Google Exec is a seasoned professional at Google. With a strong background in their field, they bring valuable expertise and leadership to the team. (Generated from https://www.linkedin.com/in/google-exec)",
      "company": "Google",
      "companyDescription": "",
      "linkedin": "https://www.linkedin.com/in/google-exec",
      "imageUrl": null,
      "isExternal": false,
      "type": "Partner"
    },
    {
      "name": "Fahad Kananen",
      "title": "OSS Sales- USA",
      "email": "fahad.kananeh@rakuten.com",
      "bio": "",
      "company": "Rakuten Symphony",
      "companyDescription": "",
      "linkedin": "",
      "imageUrl": "",
      "isExternal": false,
      "type": "Sales"
    },
    {
      "name": "Nirmal Sodani",
      "title": "APAC Sales",
      "email": "nirmal.sodani@rakuten.com",
      "bio": "",
      "company": "Rakuten Symphony",
      "companyDescription": "",
      "linkedin": "",
      "imageUrl": "",
      "isExternal": false,
      "type": "Sales"
    },
    {
      "name": "Brijesh Yadav",
      "title": "Architecture",
      "email": "brijesh.yadav@rakuten.com",
      "bio": "",
      "company": "Rakuten Mobile",
      "companyDescription": "",
      "linkedin": "",
      "imageUrl": "",
      "isExternal": false,
      "type": null
    },
    {
      "name": "Sudhakar Pandey",
      "title": "RAN",
      "email": "sudhakar.pandey@rakuten.com",
      "bio": "",
      "company": "Rakuten Mobile",
      "companyDescription": "",
      "linkedin": "",
      "imageUrl": "",
      "isExternal": false,
      "type": "BU RAN"
    },
    {
      "name": "Mitsuhiro Kuchitsu",
      "title": "Subsidy",
      "email": "mitsuhiro.kuchitsu@rakuten.com",
      "bio": "",
      "company": "Rakuten Mobile",
      "companyDescription": "",
      "linkedin": "",
      "imageUrl": "",
      "isExternal": false,
      "type": null
    },
    {
      "name": "Tadashi Tsukamoto",
      "title": "Device",
      "email": "tadashi.a.tsukamoto@rakuten.com",
      "bio": "",
      "company": "Rakuten Mobile",
      "companyDescription": "",
      "linkedin": "",
      "imageUrl": "",
      "isExternal": false,
      "type": null
    },
    {
      "name": "Ryo Watanabe",
      "title": "Core Network",
      "email": "ryo.watanabe@rakuten.com",
      "bio": "",
      "company": "Rakuten Mobile",
      "companyDescription": "",
      "linkedin": "",
      "imageUrl": "",
      "isExternal": false,
      "type": null
    },
    {
      "name": "Frederick Pion",
      "title": "Regional Director - Sales",
      "email": "frederic.pion@rakuten.com",
      "bio": "",
      "company": "Rakuten Symphony",
      "companyDescription": "",
      "linkedin": "",
      "imageUrl": "",
      "isExternal": false,
      "type": "Sales"
    },
    {
      "name": "Matan Barth",
      "title": "CPaaS Sales",
      "email": "matan.barth@rakuten.com",
      "bio": "",
      "company": "Rakuten Symphony",
      "companyDescription": "",
      "linkedin": "",
      "imageUrl": "",
      "isExternal": false,
      "type": "Sales"
    },
    {
      "name": "Mickey Mikitani",
      "title": "Group CEO",
      "email": "rsus-RS_marketing@rakuten.com",
      "bio": "",
      "company": "Rakuten Group",
      "companyDescription": "",
      "linkedin": "",
      "imageUrl": "",
      "isExternal": false,
      "type": null
    },
    {
      "name": "Sharad Sriwistawa",
      "title": "Co-CEO, President",
      "email": "sharad.sriwastawa@rakuten.com",
      "bio": "",
      "company": "Rakuten Group",
      "companyDescription": "",
      "linkedin": "",
      "imageUrl": "",
      "isExternal": false,
      "type": null
    },
    {
      "name": "Puneet Handa",
      "title": "Head of Business Strategy",
      "email": "puneet.handa@rakuten.com",
      "bio": "",
      "company": "Rakuten Mobile",
      "companyDescription": "",
      "linkedin": "",
      "imageUrl": "",
      "isExternal": false,
      "type": null
    },
    {
      "name": "Wayoh Suzuki",
      "title": "Co-CEO",
      "email": "wayoh.suzuki@rakuten.com",
      "bio": "",
      "company": "Rakuten Mobile",
      "companyDescription": "",
      "linkedin": "",
      "imageUrl": "",
      "isExternal": false,
      "type": null
    },
    {
      "name": "Sachin Verma",
      "title": "CDAIO",
      "email": "sachin.verma@rakuten.com",
      "bio": "",
      "company": "Rakuten Mobile",
      "companyDescription": "",
      "linkedin": "",
      "imageUrl": "",
      "isExternal": false,
      "type": null
    },
    {
      "name": "Mahmoud Elsakhawy",
      "title": "VP",
      "email": "mahmoud.elsakhawy@rakuten.com",
      "bio": "",
      "company": "Rakuten Mobile",
      "companyDescription": "",
      "linkedin": "",
      "imageUrl": "",
      "isExternal": false,
      "type": null
    },
    {
      "name": "Shailesh Gupta",
      "title": "Director, Network Operations (SXC) Supervisory Department",
      "email": "shailesh.b.gupta@rakuten.com",
      "bio": "",
      "company": "Rakuten Mobile",
      "companyDescription": "",
      "linkedin": "",
      "imageUrl": "",
      "isExternal": false,
      "type": null
    },
    {
      "name": "Masato Tani",
      "title": "CEO Office (under Sakuma san )",
      "email": "masato.tani@rakuten.com",
      "bio": "",
      "company": "Rakuten Group",
      "companyDescription": "",
      "linkedin": "",
      "imageUrl": "",
      "isExternal": false,
      "type": null
    },
    {
      "name": "Udai Kanukolanu",
      "title": "Global Sales Head",
      "email": "udai.kanukolanu@rakuten.com",
      "bio": "",
      "company": "Rakuten Symphony",
      "companyDescription": "",
      "linkedin": "",
      "imageUrl": "",
      "isExternal": false,
      "type": "Sales"
    },
    {
      "name": "Partha Seetala",
      "title": "BU Head",
      "email": "partha.seetala@rakuten.com",
      "bio": "",
      "company": "Rakuten Symphony",
      "companyDescription": "",
      "linkedin": "",
      "imageUrl": "",
      "isExternal": false,
      "type": "BU Cloud"
    },
    {
      "name": "Anil Sawkar",
      "title": "BU Head",
      "email": "anil.sawkar@rakuten.com",
      "bio": "",
      "company": "Rakuten Symphony",
      "companyDescription": "",
      "linkedin": "",
      "imageUrl": "",
      "isExternal": false,
      "type": "BU RAN"
    },
    {
      "name": "Vivek Murthy",
      "title": "BU Head",
      "email": "vivek.murthy@rakuten.com",
      "bio": "",
      "company": "Rakuten Symphony",
      "companyDescription": "",
      "linkedin": "",
      "imageUrl": "",
      "isExternal": false,
      "type": "BU OSS"
    },
    {
      "name": "Ryan Son",
      "title": "BU Head",
      "email": "ryan.son@rakuten.com",
      "bio": "",
      "company": "Rakuten Symphony",
      "companyDescription": "",
      "linkedin": "",
      "imageUrl": "",
      "isExternal": false,
      "type": "BU IS"
    },
    {
      "name": "Geoff Hollingworth",
      "title": "CMO",
      "email": "geoffre.hollingworth@rakuten.com",
      "bio": "",
      "company": "Rakuten Symphony",
      "companyDescription": "",
      "linkedin": "",
      "imageUrl": "",
      "isExternal": false,
      "type": "Marketing"
    },
    {
      "name": "Stefan Winter",
      "title": "RSDE MD",
      "email": "stefan.winter@rakuten.com",
      "bio": "",
      "company": "Rakuten Symphony",
      "companyDescription": "",
      "linkedin": "",
      "imageUrl": "",
      "isExternal": false,
      "type": null
    },
    {
      "name": "Masaki Koichi",
      "title": "RSJP MD",
      "email": "koichi.b.masaki@rakuten.com",
      "bio": "",
      "company": "Rakuten Symphony",
      "companyDescription": "",
      "linkedin": "",
      "imageUrl": "",
      "isExternal": false,
      "type": null
    },
    {
      "name": "Faiq Khan",
      "title": "OSS Sales",
      "email": "faiq.khan@rakuten.com",
      "bio": "",
      "company": "Rakuten Symphony",
      "companyDescription": "",
      "linkedin": "",
      "imageUrl": "",
      "isExternal": false,
      "type": "Sales"
    },
    {
      "name": "Anshul Bhatt",
      "title": "OSS Sales",
      "email": "anshul.bhatt@rakuten.com",
      "bio": "",
      "company": "Rakuten Symphony",
      "companyDescription": "",
      "linkedin": "",
      "imageUrl": "",
      "isExternal": false,
      "type": "Sales"
    },
    {
      "name": "Mina Nicola",
      "title": "OSS PreSales",
      "email": "mina.nicola@rakuten.com",
      "bio": "",
      "company": "Rakuten Symphony",
      "companyDescription": "",
      "linkedin": "",
      "imageUrl": "",
      "isExternal": false,
      "type": "Sales"
    },
    {
      "name": "Khalid El Rumman",
      "title": "OSS PreSales",
      "email": "khalid.elrumman@rakuten.com",
      "bio": "",
      "company": "Rakuten Symphony",
      "companyDescription": "",
      "linkedin": "",
      "imageUrl": "",
      "isExternal": false,
      "type": "Sales"
    },
    {
      "name": "Faisal Ghazaleh",
      "title": "OSS PreSales",
      "email": "faisal.ghazaleh@rakuten.com",
      "bio": "",
      "company": "Rakuten Symphony",
      "companyDescription": "",
      "linkedin": "",
      "imageUrl": "",
      "isExternal": false,
      "type": "Sales"
    },
    {
      "name": "Ahmed Abdelaziz",
      "title": "OSS PreSales",
      "email": "ahmed.abdelaziz@rakuten.com",
      "bio": "",
      "company": "Rakuten Symphony",
      "companyDescription": "",
      "linkedin": "",
      "imageUrl": "",
      "isExternal": false,
      "type": "Sales"
    },
    {
      "name": "Nirav Salot",
      "title": "RAN Product & Presales",
      "email": "nirav.salot@rakuten.com",
      "bio": "",
      "company": "Rakuten Symphony",
      "companyDescription": "",
      "linkedin": "",
      "imageUrl": "",
      "isExternal": false,
      "type": "Sales"
    },
    {
      "name": "Neeraj Patel",
      "title": "RAN Sales",
      "email": "neeraj.a.patel@rakuten.com",
      "bio": "",
      "company": "Rakuten Symphony",
      "companyDescription": "",
      "linkedin": "",
      "imageUrl": "",
      "isExternal": false,
      "type": "Sales"
    },
    {
      "name": "Chris Alvis",
      "title": "IS BU- CTO",
      "email": "chris.alvis@rakuten.com",
      "bio": "",
      "company": "Rakuten Symphony",
      "companyDescription": "",
      "linkedin": "",
      "imageUrl": "",
      "isExternal": false,
      "type": "BU IS"
    },
    {
      "name": "Vivek Chadha",
      "title": "TSP Sales",
      "email": "vivek.chadha@rakuten.com",
      "bio": "",
      "company": "Rakuten Symphony",
      "companyDescription": "",
      "linkedin": "",
      "imageUrl": "",
      "isExternal": false,
      "type": "Sales"
    },
    {
      "name": "Raul Carubelli",
      "title": "TSP Sales- EU",
      "email": "raul.carubelli@rakuten.com",
      "bio": "",
      "company": "Rakuten Symphony",
      "companyDescription": "",
      "linkedin": "",
      "imageUrl": "",
      "isExternal": false,
      "type": "Sales"
    },
    {
      "name": "Alberto Mendez",
      "title": "TSP- PreSales for Demos",
      "email": "alberto.mendez@rakuten.com",
      "bio": "",
      "company": "Rakuten Symphony",
      "companyDescription": "",
      "linkedin": "",
      "imageUrl": "",
      "isExternal": false,
      "type": "Sales"
    },
    {
      "name": "Anirban (Oni) Chakravartti",
      "title": "Enterprise Cloud",
      "email": "anirban.chakravartti@rakuten.com",
      "bio": "",
      "company": "Rakuten Symphony",
      "companyDescription": "",
      "linkedin": "",
      "imageUrl": "",
      "isExternal": false,
      "type": "BU Cloud"
    },
    {
      "name": "Padmarajan Narayanan",
      "title": "Enterprise Cloud",
      "email": "padmarajan.narayanan@rakuten.com",
      "bio": "",
      "company": "Rakuten Symphony",
      "companyDescription": "",
      "linkedin": "",
      "imageUrl": "",
      "isExternal": false,
      "type": "BU Cloud"
    },
    {
      "name": "Subha Shrinivasan",
      "title": "Customer Success",
      "email": "subha.shrinivasan@rakuten.com",
      "bio": "",
      "company": "Rakuten Symphony",
      "companyDescription": "",
      "linkedin": "",
      "imageUrl": "",
      "isExternal": false,
      "type": "BU Cloud"
    },
    {
      "name": "Sandeep Arora",
      "title": "APAC Sales",
      "email": "sandeep.arora@rakuten.com",
      "bio": "",
      "company": "Rakuten Symphony",
      "companyDescription": "",
      "linkedin": "",
      "imageUrl": "",
      "isExternal": false,
      "type": "Sales"
    },
    {
      "name": "Rishi Shukla",
      "title": "APAC Sales",
      "email": "rishi.shukla@rakuten.com",
      "bio": "",
      "company": "Rakuten Symphony",
      "companyDescription": "",
      "linkedin": "",
      "imageUrl": "",
      "isExternal": false,
      "type": "Sales"
    },
    {
      "name": "Shadi Sayed",
      "title": "MEA Sales",
      "email": "shadi.sayed@rakuten.com",
      "bio": "",
      "company": "Rakuten Symphony",
      "companyDescription": "",
      "linkedin": "",
      "imageUrl": "",
      "isExternal": false,
      "type": "Sales"
    },
    {
      "name": "Talaat Mohamed",
      "title": "MEA Sales",
      "email": "talaat.mohamed@rakuten.com",
      "bio": "",
      "company": "Rakuten Symphony",
      "companyDescription": "",
      "linkedin": "",
      "imageUrl": "",
      "isExternal": false,
      "type": "Sales"
    },
    {
      "name": "Swamy Vasudevan",
      "title": "US Sales",
      "email": "swamy.vasudevan@rakuten.com",
      "bio": "",
      "company": "Rakuten Symphony",
      "companyDescription": "",
      "linkedin": "",
      "imageUrl": "",
      "isExternal": false,
      "type": "Sales"
    },
    {
      "name": "Sachin Mahajan",
      "title": "Canada & partner Sales- Customer/Partner meetings",
      "email": "sachin.mahajan@rakuten.com",
      "bio": "",
      "company": "Rakuten Symphony",
      "companyDescription": "",
      "linkedin": "",
      "imageUrl": "",
      "isExternal": false,
      "type": "Sales"
    },
    {
      "name": "Alberto Rivas",
      "title": "LATAM Sales- Customer/Partner meetings",
      "email": "ts-alberto.rivas@rakuten.com",
      "bio": "",
      "company": "Rakuten Symphony",
      "companyDescription": "",
      "linkedin": "",
      "imageUrl": "",
      "isExternal": false,
      "type": "Sales"
    },
    {
      "name": "Richard Thalluri",
      "title": "LATAM Sales- Demo & Theatre Sessions",
      "email": "richard.thalluri@rakuten.com",
      "bio": "",
      "company": "Rakuten Symphony",
      "companyDescription": "",
      "linkedin": "",
      "imageUrl": "",
      "isExternal": false,
      "type": "Sales"
    },
    {
      "name": "Thomas Riedel",
      "title": "EU Sales- Customer meetings",
      "email": "thomas.riedel@rakuten.com",
      "bio": "",
      "company": "Rakuten Symphony",
      "companyDescription": "",
      "linkedin": "",
      "imageUrl": "",
      "isExternal": false,
      "type": "Sales"
    },
    {
      "name": "MiguelAngel Sanchez",
      "title": "EU Sales- Customer Meetings (Telefonica and South Europe Operators)",
      "email": "miguelangel.sanchez@rakuten.com",
      "bio": "",
      "company": "Rakuten Symphony",
      "companyDescription": "",
      "linkedin": "",
      "imageUrl": "",
      "isExternal": false,
      "type": "Sales"
    },
    {
      "name": "Wasim Saddique",
      "title": "EU Sales- Customer Meetings (UK/IRL and Nordic Operators)",
      "email": "wasim.saddique@rakuten.com",
      "bio": "",
      "company": "Rakuten Symphony",
      "companyDescription": "",
      "linkedin": "",
      "imageUrl": "",
      "isExternal": false,
      "type": "Sales"
    },
    {
      "name": "Jason King",
      "title": "Partner Mktg and Theatre Sessions",
      "email": "jason.king@rakuten.com",
      "bio": "",
      "company": "Rakuten Symphony",
      "companyDescription": "",
      "linkedin": "",
      "imageUrl": "",
      "isExternal": false,
      "type": "Marketing"
    },
    {
      "name": "Christina James",
      "title": "Demos and Operations",
      "email": "christina.pjames@rakuten.com",
      "bio": "",
      "company": "Rakuten Symphony",
      "companyDescription": "",
      "linkedin": "",
      "imageUrl": "",
      "isExternal": false,
      "type": "Marketing"
    },
    {
      "name": "Sheheryar Khakwani",
      "title": "Partner Collaboration",
      "email": "sheheryar.khakwani@rakuten.com",
      "bio": "",
      "company": "Rakuten Symphony",
      "companyDescription": "",
      "linkedin": "",
      "imageUrl": "",
      "isExternal": false,
      "type": null
    },
    {
      "name": "Shima Zeinali",
      "title": "Partner Collaboration",
      "email": "shima.a.zeinali@rakuten.com",
      "bio": "",
      "company": "Rakuten Symphony",
      "companyDescription": "",
      "linkedin": "",
      "imageUrl": "",
      "isExternal": false,
      "type": null
    },
    {
      "name": "Chetan Wani",
      "title": "President Office",
      "email": "chetan.wani@rakuten.com",
      "bio": "",
      "company": "Rakuten Symphony",
      "companyDescription": "",
      "linkedin": "",
      "imageUrl": "",
      "isExternal": false,
      "type": null
    },
    {
      "name": "Vishvesh Potdar",
      "title": "RS Japan Enterprise Sales",
      "email": "vishvesh.potdar@rakuten.com",
      "bio": "",
      "company": "Rakuten Symphony",
      "companyDescription": "",
      "linkedin": "",
      "imageUrl": "",
      "isExternal": false,
      "type": "Sales"
    },
    {
      "name": "Hiren Joshi",
      "title": "RS EU CTO",
      "email": "hiren.joshi@rakuten.com",
      "bio": "",
      "company": "Rakuten Symphony",
      "companyDescription": "",
      "linkedin": "",
      "imageUrl": "",
      "isExternal": false,
      "type": null
    },
    {
      "name": "Nagendra Bykampadi",
      "title": "Security- Speaking slot",
      "email": "nagendra.bykampadi@rakuten.com",
      "bio": "",
      "company": "Rakuten Symphony",
      "companyDescription": "",
      "linkedin": "",
      "imageUrl": "",
      "isExternal": false,
      "type": null
    },
    {
      "name": "Devesh Gautam",
      "title": "Solution Architecture",
      "email": "devesh.gautam@rakuten.com",
      "bio": "",
      "company": "Rakuten Symphony",
      "companyDescription": "",
      "linkedin": "",
      "imageUrl": "",
      "isExternal": false,
      "type": null
    },
    {
      "name": "Tarek Zeid",
      "title": "International Wholesale Business RMI",
      "email": "tarek.zeid@rakuten.com",
      "bio": "",
      "company": "Rakuten Mobile",
      "companyDescription": "",
      "linkedin": "",
      "imageUrl": "",
      "isExternal": false,
      "type": null
    },
    {
      "name": "Manal Rifki",
      "title": "International Wholesale Business RMI",
      "email": "ts-manal.rifki@rakuten.com",
      "bio": "",
      "company": "Rakuten Mobile",
      "companyDescription": "",
      "linkedin": "",
      "imageUrl": "",
      "isExternal": false,
      "type": null
    },
    {
      "name": "Polina Gardo",
      "title": "International Wholesale Business RMI",
      "email": "ts-polina.gardo@rakuten.com",
      "bio": "",
      "company": "Rakuten Mobile",
      "companyDescription": "",
      "linkedin": "",
      "imageUrl": "",
      "isExternal": false,
      "type": null
    },
    {
      "name": "Alper Tunga Burak",
      "title": "Founder & CEO",
      "email": "tbd@odine.com",
      "bio": "Alper Tunga Burak is the Founder and CEO of Odine, a leading Telco Cloud-Native OSS/BSS Systems Integrator. He has extensive experience in the telecommunications sector, driving the company's vision to provide virtualized and cloud-native solutions. Under his leadership, Odine partners with global Tier-1 operators to accelerate their digital transformation and network modernization.",
      "company": "Odine",
      "companyDescription": "Odine is a global telecommunications technology company specializing in cloud-native, virtualized OSS/BSS and orchestration solutions for Tier-1 telecom operators worldwide. They enable operators to modernize their infrastructure, streamline wholesale voice and data operations, and accelerate their digital transformation journey.",
      "linkedin": "https://www.linkedin.com/in/alpertungaburak/",
      "imageUrl": "https://image.aieventplanner.work/07312eee-9158-4d3f-a8e5-ddb1363bb0c6.jpeg",
      "isExternal": true,
      "type": "BU Cloud"
    },
    {
      "name": "Reiner",
      "title": "Hogen",
      "email": "Reiner.Hogen@fujitsu.com",
      "bio": "Reiner is a seasoned professional at Fujitsu. With a strong background in their field, they bring valuable expertise and leadership to the team. (Generated from https://www.linkedin.com/in/reiner)",
      "company": "Fujitsu",
      "companyDescription": "",
      "linkedin": "https://www.linkedin.com/in/reiner",
      "imageUrl": null,
      "isExternal": true,
      "type": "Customer"
    },
    {
      "name": "Chuck Robbins",
      "title": "CEO",
      "email": "tuutran@cisco.com",
      "bio": "For over 25 years at Cisco, Robbins has demonstrated a keen understanding of the rapidly evolving business landscape and the critical role of technology in addressing both customer and global challenges. \r\n\r\nRobbins has championed initiatives across the company to enhance employee experience and culture, contributing to Cisco earning the top spot on World’s Best Workplaces, Fortune’s 100 Best Companies to Work For, People’s Companies that Care, and various other lists throughout his tenure.\r\n\r\nPrior to becoming CEO, Robbins led Cisco’s global sales organization. He also held various leadership roles in regional sales, as well as Cisco’s partner organization, where he was instrumental in building one of the industry’s most robust partner programs.",
      "company": "Cisco",
      "companyDescription": "",
      "linkedin": "https://www.linkedin.com/in/chuck-robbins",
      "imageUrl": "https://image.aieventplanner.work/66e6a2c5-f227-497b-8ba1-bd1935c6c8d2.jpeg",
      "isExternal": true,
      "type": "Partner"
    },
    {
      "name": "Hatem",
      "title": "CEO",
      "email": "hatem@eand.com",
      "bio": "Hatem is a seasoned professional at E& Group. With a strong background in their field, they bring valuable expertise and leadership to the team. (Generated from https://www.linkedin.com/in/hatem)",
      "company": "E& Group",
      "companyDescription": "",
      "linkedin": "https://www.linkedin.com/in/hatem",
      "imageUrl": null,
      "isExternal": true,
      "type": "Customer"
    },
    {
      "name": "Hatem",
      "title": " e& Group CEO",
      "email": "anina@eand.com",
      "bio": "Hatem is a seasoned professional at E& Group. With a strong background in their field, they bring valuable expertise and leadership to the team. (Generated from https://www.linkedin.com/in/hatem)",
      "company": "E& Group",
      "companyDescription": "",
      "linkedin": "https://www.linkedin.com/in/hatem",
      "imageUrl": null,
      "isExternal": true,
      "type": "Customer"
    },
    {
      "name": "Mr. Fahad Al Hassawi",
      "title": "dU CEO ",
      "email": "Amel.mohammed@du.ae",
      "bio": "Mr. Fahad Al Hassawi is a seasoned professional at dU. With a strong background in their field, they bring valuable expertise and leadership to the team. (Generated from https://www.linkedin.com/in/mr.-fahad-al-hassawi)",
      "company": "dU",
      "companyDescription": "",
      "linkedin": "https://www.linkedin.com/in/mr.-fahad-al-hassawi",
      "imageUrl": null,
      "isExternal": true,
      "type": ""
    },
    {
      "name": "Ralph Mopito",
      "title": "MTN Group CEO",
      "email": "Ralph.Mupita@mtn.com",
      "bio": "Ralph Mopito is a seasoned professional at MTN Group. With a strong background in their field, they bring valuable expertise and leadership to the team. (Generated from https://www.linkedin.com/in/ralph-mopito)",
      "company": "MTN Group",
      "companyDescription": "",
      "linkedin": "https://www.linkedin.com/in/ralph-mopito",
      "imageUrl": null,
      "isExternal": true,
      "type": ""
    },
    {
      "name": "Kevork Kechichian",
      "title": "Executive Vice President & General Manager, Data Center Group",
      "email": "ryohei.murata@intel.com",
      "bio": "Kevork Kechichian is executive vice president and general manager of the Data Center Group (DCG) at Intel Corporation. He is responsible for Intel’s data center business, including profit and loss, roadmap, and product planning, positioning and execution.  \r\n\r\n Kevork is a proven leader with 30 years of semiconductor experience. Prior to joining Intel in 2025, he served as EVP of Solutions Engineering at Arm, where he led technology development with partner ecosystems and managed the company's transformation from IP to solutions-based approaches. He previously served as EVP of MCU/MPU Engineering at NXP Semiconductors, where he led the company’s global architecture and system-on-chip (SoC) design. He also served as SVP of Engineering at Qualcomm, where he managed the Snapdragon SoC and Technology teams and was responsible for delivering more than 100 SoCs. \r\n\r\nKevork holds a master’s in electrical engineering from Concordia University in Montreal, and a bachelor’s in electrical engineering from American University of Beirut. \r\n\r\n",
      "company": "Intel",
      "companyDescription": "",
      "linkedin": "https://www.linkedin.com/in/kevork-kechichian-981833",
      "imageUrl": "https://image.aieventplanner.work/4e249cdb-a5b9-4590-b9e9-943a253ea898.jpeg",
      "isExternal": true,
      "type": "Partner"
    },
    {
      "name": "Vivek Sood",
      "title": "Group CEO",
      "email": "vivek@axiata.com",
      "bio": "Vivek Sood is a seasoned professional at Axia. With a strong background in their field, they bring valuable expertise and leadership to the team. (Generated from https://www.linkedin.com/in/vivek-sood)",
      "company": "Axia",
      "companyDescription": "",
      "linkedin": "https://www.linkedin.com/in/vivek-sood",
      "imageUrl": null,
      "isExternal": true,
      "type": "Customer"
    },
    {
      "name": "Dr Tomek Gerszberg",
      "title": "Technology Strategy",
      "email": "tomek@axiata.com",
      "bio": "Dr Tomek Gerszberg is a seasoned professional at Axiata. With a strong background in their field, they bring valuable expertise and leadership to the team. (Generated from https://www.linkedin.com/in/dr-tomek-gerszberg)",
      "company": "Axiata",
      "companyDescription": "",
      "linkedin": "https://www.linkedin.com/in/dr-tomek-gerszberg",
      "imageUrl": null,
      "isExternal": true,
      "type": "Customer"
    },
    {
      "name": "Anthony Rodrigo",
      "title": "Group CIO /CEO Axiata Digital Labs",
      "email": "anthony.rodrigo@axiata.com",
      "bio": "Anthony Rodrigo is a seasoned professional at Axiata Digital Labs. With a strong background in their field, they bring valuable expertise and leadership to the team. (Generated from https://www.linkedin.com/in/anthony-rodrigo)",
      "company": "Axiata Digital Labs",
      "companyDescription": "",
      "linkedin": "https://www.linkedin.com/in/anthony-rodrigo",
      "imageUrl": null,
      "isExternal": true,
      "type": "Customer"
    },
    {
      "name": "Gregory Ernst ",
      "title": "Corporate Vice President & Chief Revenue Officer, General Manager of Sales and Marketing Group",
      "email": "TBD@intel.com",
      "bio": "Gregory (Greg) Ernst is corporate vice president, chief revenue officer and general manager of the Sales and Marketing Group at Intel Corporation. In his role, Ernst oversees Intel’s global sales, marketing, customer support and customer success teams. He leads the company’s efforts to deepen customer relationships, drive customer and partner success, and foster sales and marketing approaches that broaden Intel’s business opportunities.\r\n\r\nErnst joined Intel in 1999. Throughout his career at Intel, he has held leadership roles across Intel’s Cisco, Dell, Hewlett-Packard Enterprise and HP Inc. sales account teams. He has also served as vice president in the Sales and Marketing Group and as general manager of United States sales.\r\n\r\nPrior to his role as chief revenue officer, Ernst served as corporate vice president and general manager of the Americas region for Intel. In this role, he led the team of sellers and marketers that support all Americas-based customers and partners.\r\n\r\nErnst holds a bachelor’s degree in electrical engineering from the University of Texas at Austin.",
      "company": "Intel",
      "companyDescription": "",
      "linkedin": "https://www.linkedin.com/in/gregory-ernst-",
      "imageUrl": "https://image.aieventplanner.work/e832457a-48e9-4b6c-958c-ae215a5d1548.jpeg",
      "isExternal": true,
      "type": "Partner"
    },
    {
      "name": "Kumar N Sivarajan",
      "title": "CTO Tejas Networks",
      "email": "kumar@tejasnetworks.com",
      "bio": "Kumar N Sivarajan is a seasoned professional at Tejas Networks. With a strong background in their field, they bring valuable expertise and leadership to the team. (Generated from https://www.linkedin.com/in/kumar-n-sivarajan)",
      "company": "Tejas Networks",
      "companyDescription": "",
      "linkedin": "https://www.linkedin.com/in/kumar-n-sivarajan",
      "imageUrl": null,
      "isExternal": true,
      "type": ""
    },
    {
      "name": "Dr. Mothilal de Silva",
      "title": "Chairman",
      "email": "Chairman@slt.com.lk",
      "bio": "Dr. Mothilal de Silva is a seasoned professional at SriLanka Telecom. With a strong background in their field, they bring valuable expertise and leadership to the team. (Generated from https://www.linkedin.com/in/dr.-mothilal-de-silva)",
      "company": "SriLanka Telecom",
      "companyDescription": "",
      "linkedin": "https://www.linkedin.com/in/dr.-mothilal-de-silva",
      "imageUrl": null,
      "isExternal": true,
      "type": "Customer"
    },
    {
      "name": "Sudharshana Geeganage",
      "title": "COO",
      "email": "sudharshanag@mobitel.lk",
      "bio": "Sudharshana Geeganage is a seasoned professional at SriLanka Telecom. With a strong background in their field, they bring valuable expertise and leadership to the team. (Generated from https://www.linkedin.com/in/sudharshana-geeganage)",
      "company": "SriLanka Telecom",
      "companyDescription": "",
      "linkedin": "https://www.linkedin.com/in/sudharshana-geeganage",
      "imageUrl": null,
      "isExternal": true,
      "type": "Customer"
    },
    {
      "name": "Indika Asurappulige",
      "title": "Head of Networks",
      "email": "indikan@mobitel.lk",
      "bio": "Indika Asurappulige is a seasoned professional at SriLanka Telecom. With a strong background in their field, they bring valuable expertise and leadership to the team. (Generated from https://www.linkedin.com/in/indika-asurappulige)",
      "company": "SriLanka Telecom",
      "companyDescription": "",
      "linkedin": "https://www.linkedin.com/in/indika-asurappulige",
      "imageUrl": null,
      "isExternal": true,
      "type": "Customer"
    },
    {
      "name": "Abbi Pilapitiya",
      "title": "CEO",
      "email": "abbi.pilapitiya@sierra.lk",
      "bio": "Abbi Pilapitiya is a seasoned professional at SIERRA. With a strong background in their field, they bring valuable expertise and leadership to the team. (Generated from https://www.linkedin.com/in/abbi-pilapitiya)",
      "company": "SIERRA",
      "companyDescription": "",
      "linkedin": "https://www.linkedin.com/in/abbi-pilapitiya",
      "imageUrl": null,
      "isExternal": true,
      "type": "Partner"
    },
    {
      "name": "Rade Kovacevic",
      "title": "Head of Sourcing",
      "email": "rade.kovacevic@telenor.com",
      "bio": "Rade Kovacevic is a seasoned professional at Telenor. With a strong background in their field, they bring valuable expertise and leadership to the team. (Generated from https://www.linkedin.com/in/rade-kovacevic)",
      "company": "Telenor",
      "companyDescription": "",
      "linkedin": "https://www.linkedin.com/in/rade-kovacevic",
      "imageUrl": null,
      "isExternal": true,
      "type": "Customer"
    },
    {
      "name": "Mr.Raja Halder",
      "title": "Head of Network Sourcing ",
      "email": "raja.haldar@telenor.com",
      "bio": "Mr.Raja Halder is a seasoned professional at Telenor Procurement Company. With a strong background in their field, they bring valuable expertise and leadership to the team. (Generated from https://www.linkedin.com/in/mr.raja-halder)",
      "company": "Telenor Procurement Company",
      "companyDescription": "",
      "linkedin": "https://www.linkedin.com/in/mr.raja-halder",
      "imageUrl": null,
      "isExternal": true,
      "type": "Customer"
    },
    {
      "name": "Shanshil Ahmed Shibly",
      "title": "Asia Technology Head ",
      "email": "shanshil.shibly@telenor.com",
      "bio": "Shanshil Ahmed Shibly is a seasoned professional at Telenor. With a strong background in their field, they bring valuable expertise and leadership to the team. (Generated from https://www.linkedin.com/in/shanshil-ahmed-shibly)",
      "company": "Telenor",
      "companyDescription": "",
      "linkedin": "https://www.linkedin.com/in/shanshil-ahmed-shibly",
      "imageUrl": null,
      "isExternal": true,
      "type": "Customer"
    },
    {
      "name": "Daaij Al-Oud",
      "title": "CTO",
      "email": "daaij.aloud@kw.zain.com",
      "bio": "Daaij Al-Oud is a seasoned professional at Zain Kuwait. With a strong background in their field, they bring valuable expertise and leadership to the team. (Generated from https://www.linkedin.com/in/daaij-al-oud)",
      "company": "Zain Kuwait",
      "companyDescription": "",
      "linkedin": "https://www.linkedin.com/in/daaij-al-oud",
      "imageUrl": null,
      "isExternal": true,
      "type": "Customer"
    },
    {
      "name": "Nawaf Algharabally",
      "title": "CEO",
      "email": "nawaf.algharabally@kw.zain.com",
      "bio": "Nawaf Algharabally is a seasoned professional at Zain Kuwait. With a strong background in their field, they bring valuable expertise and leadership to the team. (Generated from https://www.linkedin.com/in/nawaf-algharabally)",
      "company": "Zain Kuwait",
      "companyDescription": "",
      "linkedin": "https://www.linkedin.com/in/nawaf-algharabally",
      "imageUrl": null,
      "isExternal": false,
      "type": "Customer"
    },
    {
      "name": "Thomas Hundt",
      "title": "Group CTO",
      "email": "thomas.hundt@axiata.com",
      "bio": "Thomas Hundt is a seasoned professional at Axiata. With a strong background in their field, they bring valuable expertise and leadership to the team. (Generated from https://www.linkedin.com/in/thomas-hundt)",
      "company": "Axiata",
      "companyDescription": "",
      "linkedin": "https://www.linkedin.com/in/thomas-hundt",
      "imageUrl": null,
      "isExternal": true,
      "type": "Customer"
    },
    {
      "name": "Olayan M. Alwetaid",
      "title": "CEO",
      "email": "uwetaid@stc.com.sa",
      "bio": "Olayan M. Alwetaid is a seasoned professional at STC. With a strong background in their field, they bring valuable expertise and leadership to the team. (Generated from https://www.linkedin.com/in/olayan-m.-alwetaid)",
      "company": "STC",
      "companyDescription": "",
      "linkedin": "https://www.linkedin.com/in/olayan-m.-alwetaid",
      "imageUrl": null,
      "isExternal": true,
      "type": "Customer"
    },
    {
      "name": "Mr. Abdulrahman Al Moaiqe",
      "title": "COO",
      "email": "amoaiqel@tawal.com.sa",
      "bio": "Mr. Abdulrahman Al Moaiqe is a seasoned professional at Tawal. With a strong background in their field, they bring valuable expertise and leadership to the team. (Generated from https://www.linkedin.com/in/mr.-abdulrahman-al-moaiqe)",
      "company": "Tawal",
      "companyDescription": "",
      "linkedin": "https://www.linkedin.com/in/mr.-abdulrahman-al-moaiqe",
      "imageUrl": null,
      "isExternal": true,
      "type": "Customer"
    },
    {
      "name": "Aziz Aluthman Fakhroo",
      "title": "Group CEO",
      "email": "afakhroo@qm.org.qa",
      "bio": "Aziz Aluthman Fakhroo is a seasoned professional at Ooredoo. With a strong background in their field, they bring valuable expertise and leadership to the team. (Generated from https://www.linkedin.com/in/aziz-aluthman-fakhroo)",
      "company": "Ooredoo",
      "companyDescription": "",
      "linkedin": "https://www.linkedin.com/in/aziz-aluthman-fakhroo",
      "imageUrl": null,
      "isExternal": true,
      "type": "Customer"
    },
    {
      "name": "Sunil Taldar",
      "title": "CEO",
      "email": "sunil.taldar@africa.airtel.com",
      "bio": "Sunil Taldar is a seasoned professional at Airtel Africa. With a strong background in their field, they bring valuable expertise and leadership to the team. (Generated from https://www.linkedin.com/in/sunil-taldar)",
      "company": "Airtel Africa",
      "companyDescription": "",
      "linkedin": "https://www.linkedin.com/in/sunil-taldar",
      "imageUrl": null,
      "isExternal": true,
      "type": "Customer"
    },
    {
      "name": "Shashwat sharma",
      "title": "CEO",
      "email": "shashwat.sharma@airtel.com",
      "bio": "Shashwat sharma is a seasoned professional at Airtel. With a strong background in their field, they bring valuable expertise and leadership to the team. (Generated from https://www.linkedin.com/in/shashwat-sharma)",
      "company": "Airtel",
      "companyDescription": "",
      "linkedin": "https://www.linkedin.com/in/shashwat-sharma",
      "imageUrl": null,
      "isExternal": true,
      "type": "Customer"
    },
    {
      "name": "Mr.Vinh Tuan Bao",
      "title": "CTO",
      "email": "bao.vinh@mobifone.vn",
      "bio": "Mr.Vinh Tuan Bao is a seasoned professional at Mobifone. With a strong background in their field, they bring valuable expertise and leadership to the team. (Generated from https://www.linkedin.com/in/mr.vinh-tuan-bao)",
      "company": "Mobifone",
      "companyDescription": "",
      "linkedin": "https://www.linkedin.com/in/mr.vinh-tuan-bao",
      "imageUrl": null,
      "isExternal": true,
      "type": "Customer"
    },
    {
      "name": "Desmond Cheung",
      "title": "CTO",
      "email": "desmond.cheung@ioh.co.id",
      "bio": "Desmond Cheung is a seasoned professional at IOH. With a strong background in their field, they bring valuable expertise and leadership to the team. (Generated from https://www.linkedin.com/in/desmond-cheung)",
      "company": "IOH",
      "companyDescription": "",
      "linkedin": "https://www.linkedin.com/in/desmond-cheung",
      "imageUrl": null,
      "isExternal": true,
      "type": "Customer"
    },
    {
      "name": "Luthfi Auzan",
      "title": "VP Network Operations",
      "email": "luthfi.auzan@ioh.co.id",
      "bio": "Luthfi Auzan is a seasoned professional at IOH. With a strong background in their field, they bring valuable expertise and leadership to the team. (Generated from https://www.linkedin.com/in/luthfi-auzan)",
      "company": "IOH",
      "companyDescription": "",
      "linkedin": "https://www.linkedin.com/in/luthfi-auzan",
      "imageUrl": null,
      "isExternal": true,
      "type": "Customer"
    },
    {
      "name": "Nikhil Eapen",
      "title": "CEO",
      "email": "nikhile@starhub.com",
      "bio": "Nikhil Eapen is a seasoned professional at StarHub. With a strong background in their field, they bring valuable expertise and leadership to the team. (Generated from https://www.linkedin.com/in/nikhil-eapen)",
      "company": "StarHub",
      "companyDescription": "",
      "linkedin": "https://www.linkedin.com/in/nikhil-eapen",
      "imageUrl": null,
      "isExternal": true,
      "type": "Customer"
    },
    {
      "name": "Yuen Kuan Moon",
      "title": "CEO",
      "email": "kmyuen@singtel.com",
      "bio": "Yuen Kuan Moon is a seasoned professional at Singtel. With a strong background in their field, they bring valuable expertise and leadership to the team. (Generated from https://www.linkedin.com/in/yuen-kuan-moon)",
      "company": "Singtel",
      "companyDescription": "",
      "linkedin": "https://www.linkedin.com/in/yuen-kuan-moon",
      "imageUrl": null,
      "isExternal": true,
      "type": "Customer"
    },
    {
      "name": "Jorge Fernandes",
      "title": "CTO",
      "email": "jorge.fernandes@singtel.com",
      "bio": "Jorge Fernandes is a seasoned professional at Sing. With a strong background in their field, they bring valuable expertise and leadership to the team. (Generated from https://www.linkedin.com/in/jorge-fernandes)",
      "company": "Sing",
      "companyDescription": "",
      "linkedin": "https://www.linkedin.com/in/jorge-fernandes",
      "imageUrl": null,
      "isExternal": true,
      "type": "Customer"
    },
    {
      "name": "Jai Prakash",
      "title": "CTO",
      "email": "jai.prakash@grameenphone.com",
      "bio": "Jai Prakash is a seasoned professional at Grameenphone. With a strong background in their field, they bring valuable expertise and leadership to the team. (Generated from https://www.linkedin.com/in/jai-prakash)",
      "company": "Grameenphone",
      "companyDescription": "",
      "linkedin": "https://www.linkedin.com/in/jai-prakash",
      "imageUrl": null,
      "isExternal": true,
      "type": "Customer"
    },
    {
      "name": "Md. Abu Baker Shibly",
      "title": "Technology Strategy & Transformation Technology",
      "email": "abshibly@grameenphone.com",
      "bio": "Md. Abu Baker Shibly is a seasoned professional at Grameenphone. With a strong background in their field, they bring valuable expertise and leadership to the team. (Generated from https://www.linkedin.com/in/md.-abu-baker-shibly)",
      "company": "Grameenphone",
      "companyDescription": "",
      "linkedin": "https://www.linkedin.com/in/md.-abu-baker-shibly",
      "imageUrl": null,
      "isExternal": true,
      "type": "Customer"
    }
  ],
  "rooms": [
    {
      "name": "Meeting Room 1 (Mickey)",
      "capacity": 10
    },
    {
      "name": "Meeting Room 3",
      "capacity": 6
    },
    {
      "name": "Meeting Room 4",
      "capacity": 6
    },
    {
      "name": "Meeting Room 5",
      "capacity": 6
    },
    {
      "name": "Meeting Room 6",
      "capacity": 6
    },
    {
      "name": "Meeting Room 2 (Sharad)",
      "capacity": 8
    }
  ],
  "meetings": [
    {
      "title": "Rakuten - E& Group",
      "purpose": "PURPOSE:\nExecutive Trust & Relationship Established\nCommitment to Tokyo HQ visit confirmed\n90-day acceleration plan agreed\nStrategic partnership discussions initiated\nClear differentiation from vendor relationships\n\nAGENDA:\nWelcome & Context\nRakuten Group, Rakuten Mobile & Symphony\ne& Group's Strategic Vision & Priorities\nStrategic Partnership Framework & Next Steps\n",
      "date": "2026-03-02",
      "startTime": "14:00",
      "endTime": "14:30",
      "sequence": 1,
      "status": "PIPELINE",
      "tags": [
        "MEA"
      ],
      "createdBy": "ts-deepa.shanker@rakuten.com",
      "requesterEmail": "shadi.sayed@rakuten.com",
      "meetingType": "Sales/Customer",
      "location": null,
      "otherDetails": "",
      "isApproved": false,
      "calendarInviteSent": false,
      "room": "Meeting Room 1 (Mickey)",
      "attendees": [
        "rsus-RS_marketing@rakuten.com",
        "sharad.sriwastawa@rakuten.com",
        "udai.kanukolanu@rakuten.com",
        "sandeep.arora@rakuten.com",
        "shadi.sayed@rakuten.com",
        "hatem@eand.com",
        "anina@eand.com"
      ]
    },
    {
      "title": "Oracle x Rakuten",
      "purpose": "Ongoing Business with rakuten , Global experience and Roadmap Oracle ",
      "date": null,
      "startTime": "09:00",
      "endTime": "09:30",
      "sequence": 1,
      "status": "PIPELINE",
      "tags": [],
      "createdBy": "yuno.kido@rakuten.com",
      "requesterEmail": "anil.munde@oracle.com",
      "meetingType": "Vendor Partner",
      "location": null,
      "otherDetails": "Purpose /Objective   -  Executive catch up ,Oracle Technology  Roadmap with Open AI .\n\nRequestor  -  Anil Munde  -Regional Sales Director\n\nAttendee -\n\n  Payam Sharifi  - SVP - Head Of Sales CGIU\n\n  Nuno Saraiva - VP  Sales Consulting\n\n  Alex Hunte   -  Senior Director, Head of Communication GIU Sales, \n\n  JAPAC.\n\nLocation /Booth   - Oracle Booth as per invitation letter attached or Rakuten Booth \n\n Duration -    30 min \n\n Date   -  2 March / 3 March 2026\n\nBackground --  Ongoing Business with rakuten , Global experience and Roadmap Oracle ",
      "isApproved": false,
      "calendarInviteSent": false,
      "room": "Meeting Room 2 (Sharad)",
      "attendees": [
        "sharad.sriwastawa@rakuten.com"
      ]
    },
    {
      "title": "Gigs x Rakuten ",
      "purpose": "Rakuten Mobile executive team asked to meet with Gigs in December after introduction from Rakuten Capital. The initial context of the December 22nd meeting was to primarily scope working with Rakuten Mobile as a carrier - for international roaming or in the future for a larger relationship in Japan. This was an intorductory meeting between both parties. As a follow-up Sharad and Hermann wanted to use the opportunity at MWC to meet in-person to foster executive strategic alignment in the future.  ",
      "date": null,
      "startTime": null,
      "endTime": null,
      "sequence": 0,
      "status": "PIPELINE",
      "tags": [],
      "createdBy": "yuno.kido@rakuten.com",
      "requesterEmail": "nandi@gigs.com",
      "meetingType": "Vendor Partner",
      "location": null,
      "otherDetails": "■Purpose/Objective: Executive Meeting with Gigs CEO as a follow-up from meeting on December 22nd \n\n■Requestor: Nandi Radmer (Gigs)\n\n■Attendees(with title): Hermann (Gigs CEO and Co-Founder), Nandi (Lead Strategic Projects), Lo (Chief of Staff to Hermann)\n\n■Location(Booth): Rakuten booth\n\n■Duration: 30mins\n\n■Date: March 3rd or 4th mid-morning or early afternoon\n\n■Background (If possible): Rakuten Mobile executive team asked to meet with Gigs in December after introduction from Rakuten Capital. The initial context of the December 22nd meeting was to primarily scope working with Rakuten Mobile as a carrier - for international roaming or in the future for a larger relationship in Japan. This was an intorductory meeting between both parties. As a follow-up Sharad and Hermann wanted to use the opportunity at MWC to meet in-person to foster executive strategic alignment in the future.  ",
      "isApproved": false,
      "calendarInviteSent": false,
      "room": "Meeting Room 2 (Sharad)",
      "attendees": [
        "sharad.sriwastawa@rakuten.com"
      ]
    },
    {
      "title": "Fujitsu / Rakuten Symphony",
      "purpose": "",
      "date": "2026-03-03",
      "startTime": "09:30",
      "endTime": "10:00",
      "sequence": 2,
      "status": "CONFIRMED",
      "tags": [
        "Europe"
      ],
      "createdBy": "monica.cuellar@rakuten.com",
      "requesterEmail": "thomas.riedel@rakuten.com",
      "meetingType": "Sales/Customer",
      "location": null,
      "otherDetails": "From Fujitsu side will also attend Lytsikas, Lambis",
      "isApproved": false,
      "calendarInviteSent": false,
      "room": "Meeting Room 4",
      "attendees": [
        "thomas.riedel@rakuten.com",
        "Reiner.Hogen@fujitsu.com"
      ]
    },
    {
      "title": "MTG with NSSOL/ Masaki & Vishvesh",
      "purpose": "・Introduction\n・Exchanging Industry information\n・Discussions on collaboration/ partnership opportunities in Japan. ",
      "date": "2026-03-02",
      "startTime": "13:00",
      "endTime": "14:00",
      "sequence": 2,
      "status": "CONFIRMED",
      "tags": [
        "Japan Enterprise"
      ],
      "createdBy": "tharusha.mukundadura@rakuten.com",
      "requesterEmail": "tharusha.mukundadura@rakuten.com",
      "meetingType": "Sales/Customer",
      "location": null,
      "otherDetails": "Participant details:\nRS: Japan Enterprise_ Masaki & Vishvesh\nNSSOL side: Noro, Miura, Nishi",
      "isApproved": false,
      "calendarInviteSent": false,
      "room": "Meeting Room 3",
      "attendees": [
        "koichi.b.masaki@rakuten.com",
        "vishvesh.potdar@rakuten.com"
      ]
    },
    {
      "title": "Rakuten -  Tejas",
      "purpose": "Agenda:\nDU and CU – design and manufacturing for low ARPU mkt\nRU availability in n77 and n50 band\nLTE – OPEN RAN like 5G\n2G support\nGTM Model with RACI between RS and Tejas\nPrivate 5G discussion",
      "date": "2026-03-03",
      "startTime": "10:00",
      "endTime": "10:30",
      "sequence": 3,
      "status": "PIPELINE",
      "tags": [
        "APAC"
      ],
      "createdBy": "ts-deepa.shanker@rakuten.com",
      "requesterEmail": "rishi.shukla@rakuten.com",
      "meetingType": "Vendor Partner",
      "location": null,
      "otherDetails": "Rakuten Booth #2C70 ",
      "isApproved": false,
      "calendarInviteSent": false,
      "room": "Meeting Room 2 (Sharad)",
      "attendees": [
        "nirmal.sodani@rakuten.com",
        "sharad.sriwastawa@rakuten.com",
        "udai.kanukolanu@rakuten.com",
        "sandeep.arora@rakuten.com",
        "rishi.shukla@rakuten.com",
        "kumar@tejasnetworks.com"
      ]
    },
    {
      "title": "Odine x Rakuten Symphony",
      "purpose": "",
      "date": null,
      "startTime": "09:00",
      "endTime": "09:30",
      "sequence": 6,
      "status": "PIPELINE",
      "tags": [
        "Cloud"
      ],
      "createdBy": "jessica.cheng@rakuten.com",
      "requesterEmail": "anirban.chakravartti@rakuten.com",
      "meetingType": "Channel Partner",
      "location": null,
      "otherDetails": "",
      "isApproved": false,
      "calendarInviteSent": false,
      "attendees": [
        "partha.seetala@rakuten.com",
        "anirban.chakravartti@rakuten.com",
        "tbd@odine.com"
      ]
    },
    {
      "title": "Cisco x Rakuten",
      "purpose": "- Executive connect on project status\n- Key partner of FY2026\n- Group photos (end-of-meeting)",
      "date": "2026-03-03",
      "startTime": "10:00",
      "endTime": "10:30",
      "sequence": 2,
      "status": "PIPELINE",
      "tags": [
        "Global"
      ],
      "createdBy": "jessica.cheng@rakuten.com",
      "requesterEmail": "bcamoens@cisco.com",
      "meetingType": "Technology Partner",
      "location": null,
      "otherDetails": "Cisco provides networking hardware, software, telecommunications equipment and other high-technology services and products. RMI has been deployed Cisco SP router, Edge Switches, DC Switches, Packet Core, and closely work with Cisco CX team to develop and operate. ",
      "isApproved": false,
      "calendarInviteSent": false,
      "room": "Meeting Room 1 (Mickey)",
      "attendees": [
        "rsus-RS_marketing@rakuten.com",
        "tuutran@cisco.com"
      ]
    },
    {
      "title": "Google x Sharad Executive Dinner",
      "purpose": "",
      "date": "2026-03-03",
      "startTime": "19:00",
      "endTime": "21:00",
      "sequence": 3,
      "status": "PIPELINE",
      "tags": [],
      "createdBy": "yuno.kido@rakuten.com",
      "requesterEmail": "jessica.cheng@rakuten.com",
      "meetingType": "Other",
      "location": null,
      "otherDetails": "Date/time: Mar 3, Tuesday @ 7pm CET\nLocation: TBD \nGoogle Executives:\nManinder S - VP and Head and Google Cloud Product and GM\nManu Batra - Head of Product for Google DC servers\nRS attendees:\nSharad\nPartha\nOni",
      "isApproved": false,
      "calendarInviteSent": false,
      "attendees": [
        "sharad.sriwastawa@rakuten.com",
        "partha.seetala@rakuten.com",
        "anirban.chakravartti@rakuten.com"
      ]
    },
    {
      "title": "SLT & Sierra - Rakuten Symphony",
      "purpose": "Agenda:\nGreetings and appreciation for SLT/Mobitel leadership’s time at MWC\nBrief introductions of delegations\nContext setting: strategic engagement between SLT/Mobitel and Rakuten Symphony\nShared vision for future-ready mobile networks\nSLT/Mobitel’s intent to:\nExpand mobile network capacity and coverage\nDiversify vendor ecosystem with non-Chinese suppliers\nAccelerate network automation and AI-driven operation",
      "date": "2026-03-02",
      "startTime": "15:00",
      "endTime": "15:30",
      "sequence": 0,
      "status": "PIPELINE",
      "tags": [
        "APAC"
      ],
      "createdBy": "ts-deepa.shanker@rakuten.com",
      "requesterEmail": "rishi.shukla@rakuten.com",
      "meetingType": "Sales/Customer",
      "location": null,
      "otherDetails": "",
      "isApproved": false,
      "calendarInviteSent": false,
      "room": "Meeting Room 2 (Sharad)",
      "attendees": [
        "nirmal.sodani@rakuten.com",
        "udai.kanukolanu@rakuten.com",
        "sandeep.arora@rakuten.com",
        "rishi.shukla@rakuten.com",
        "Chairman@slt.com.lk",
        "sudharshanag@mobitel.lk",
        "indikan@mobitel.lk",
        "abbi.pilapitiya@sierra.lk"
      ]
    },
    {
      "title": "dU -Rakuten",
      "purpose": "PURPOSE:\nExecutive trust and relationship established\nCommitment to Tokyo HQ visit confirmed\n90-day acceleration plan agreed\nStrategic partnership discussions initiated\nClear differentiation from vendor relationships\n\nAGENDA\nWelcome & Context\nRakuten Group , Rakuten Mobile & Symphony\ndU's Strategic Vision & Priorities\nStrategic Partnership Framework & Next Steps",
      "date": "2026-03-03",
      "startTime": "10:30",
      "endTime": "11:00",
      "sequence": 3,
      "status": "PIPELINE",
      "tags": [
        "MEA"
      ],
      "createdBy": "ts-deepa.shanker@rakuten.com",
      "requesterEmail": "shadi.sayed@rakuten.com",
      "meetingType": "Sales/Customer",
      "location": null,
      "otherDetails": "",
      "isApproved": false,
      "calendarInviteSent": false,
      "room": "Meeting Room 1 (Mickey)",
      "attendees": [
        "rsus-RS_marketing@rakuten.com",
        "sharad.sriwastawa@rakuten.com",
        "udai.kanukolanu@rakuten.com",
        "sandeep.arora@rakuten.com",
        "shadi.sayed@rakuten.com",
        "Amel.mohammed@du.ae"
      ]
    },
    {
      "title": "Telenor - Rakuten Symphony",
      "purpose": " strengthening engagement and aligning on future network strategy\n   Telenor’s focus on:\nScalable and cost-efficient mobile network expansion of ongoing Graeenphone POC\nccelerated adoption of cloud-native, Open RAN, and automation-led networks",
      "date": "2026-03-02",
      "startTime": "14:30",
      "endTime": "15:00",
      "sequence": 0,
      "status": "PIPELINE",
      "tags": [
        "APAC"
      ],
      "createdBy": "ts-deepa.shanker@rakuten.com",
      "requesterEmail": "rishi.shukla@rakuten.com",
      "meetingType": "Sales/Customer",
      "location": null,
      "otherDetails": "",
      "isApproved": false,
      "calendarInviteSent": false,
      "room": "Meeting Room 1 (Mickey)",
      "attendees": [
        "rsus-RS_marketing@rakuten.com",
        "sharad.sriwastawa@rakuten.com",
        "udai.kanukolanu@rakuten.com",
        "sandeep.arora@rakuten.com",
        "rishi.shukla@rakuten.com",
        "rade.kovacevic@telenor.com",
        "raja.haldar@telenor.com",
        "shanshil.shibly@telenor.com"
      ]
    },
    {
      "title": "Thales DIS Japan x Rakuten",
      "purpose": "For strong partnership with Rakuten in 2026, Thales wants to listen the requirement from Rakuten(support, new technology, innovation for Rakuten,,,)\n\nFrom Thales, we will plan to share eSIM/IoT global trend update",
      "date": null,
      "startTime": "09:00",
      "endTime": "09:30",
      "sequence": 3,
      "status": "PIPELINE",
      "tags": [],
      "createdBy": "yuno.kido@rakuten.com",
      "requesterEmail": "daisuke.sasaki@thalesgroup.com",
      "meetingType": "Vendor Partner",
      "location": null,
      "otherDetails": "■Purpose/Objective : For strong partnership with Rakuten in 2026, Thales wants to listen the requirement from Rakuten(support, new technology, innovation for Rakuten,,,)\nFrom Thales, we will plan to share eSIM/IoT global trend update\n\n■Requestor : Mr. Daisuke Sasaki - Thales DIS Japan\n\n■Attendees(with title) : -RUDIN Eva (VP, Head of Mobile Connectivity Solutions)\n\n-OUILLET Jean-Francois (Global Head of Sales, Mobile Connectivity Solutions)\n\n-MICHAUX Bertrand (Vice President, Sales Mobile Connectivity Solutions Japan)\n\n \n\n■Location(Booth) : Rakuten Booth (?)\n\n■Duration : 30min\n\n■Date : We would like to know the current available slots of Mr.Sharad\n\n■Background (If possible) : Our management (Eva/JFO)met Mr.Sharad on May 2025 at Rakuten office and we would like to keep our strong relationship with Rakuten with arranging  \n\nthe  meeting.",
      "isApproved": false,
      "calendarInviteSent": false,
      "room": "Meeting Room 2 (Sharad)",
      "attendees": [
        "sharad.sriwastawa@rakuten.com"
      ]
    },
    {
      "title": "Intel x Rakuten Symphony",
      "purpose": "This would be the first meeting opportunity for both executives with Mickey-san and Sharad.\nWhile I understand they have already met with our CEO Lip Bu Tan, we believe MWC'26 presents an excellent opportunity to further strengthen our executive relationships\n",
      "date": "2026-03-03",
      "startTime": "11:00",
      "endTime": "11:30",
      "sequence": 1,
      "status": "PIPELINE",
      "tags": [
        "Partner"
      ],
      "createdBy": "jessica.cheng@rakuten.com",
      "requesterEmail": "ryohei.murata@intel.com",
      "meetingType": "Technology Partner",
      "location": null,
      "otherDetails": "Executive Capabilities:\nKevork leads our Intel® Xeon® 6 Processors business unit and would provide valuable insights on product feedback and future collaboration opportunities\nGreg heads our Sales organization and could discuss the strategic sales support needed\nAdditionally, Cristina Rodriguez, our former GM of the Network and Edge Group(now all under Kevork), is also planned to attend and could join these discussions.",
      "isApproved": false,
      "calendarInviteSent": false,
      "room": "Meeting Room 1 (Mickey)",
      "attendees": [
        "rsus-RS_marketing@rakuten.com",
        "ryohei.murata@intel.com",
        "TBD@intel.com"
      ]
    },
    {
      "title": "Cisco (Masum) x Rakuten",
      "purpose": "In order to follow up together about Rakuten 5GC project and Rakuten Symphony partnership on executive level.",
      "date": "2026-03-04",
      "startTime": "11:00",
      "endTime": "11:45",
      "sequence": 1,
      "status": "PIPELINE",
      "tags": [],
      "createdBy": "yuno.kido@rakuten.com",
      "requesterEmail": "shusui@cisco.com",
      "meetingType": "Vendor Partner",
      "location": null,
      "otherDetails": "3.Sharad - Masum (Head of Mobility business unit)\n\n■Date/Time : Wed - Mar 04, 11:00 AM - 11:45 AM\n\n■Purpose/Objective : Update RMI 5GC Project and Rakuten Symphony ORAN partnership \n\n■Requestor : Shibasaki-san (Cisco)\n\n■Attendees(with title) :\n・Masum Mir（SVP/GM, Provider Mobility, Cisco）\n・Vish Iyer（SVP APJ SP, Cisco）\n・Bob Everson（Chief Architect, Cisco）\n・Toshimichi Kida（Managing Director, Japan SP, Cisco）\n・Hiroshi Tokai（Client Director, Rakuten, Cisco）\n・Mohammed Awad（Leader, Global Sales, Cisco）\n・Yoshiki Yamada（JP SE Manager, Cisco）\n\n■Location(Booth) : Rakuten booth\n\n We secured a meeting room just in case. Locations of Rakuten & Cisco booths are actually nearby.\n\n■Background (If possible) :\nIn order to follow up together about Rakuten 5GC project and Rakuten Symphony partnership on executive level.",
      "isApproved": false,
      "calendarInviteSent": false,
      "room": "Meeting Room 2 (Sharad)",
      "attendees": [
        "sharad.sriwastawa@rakuten.com"
      ]
    },
    {
      "title": "Grameenphone - ",
      "purpose": "",
      "date": "2026-03-02",
      "startTime": "09:00",
      "endTime": "09:30",
      "sequence": 0,
      "status": "PIPELINE",
      "tags": [],
      "createdBy": "ts-deepa.shanker@rakuten.com",
      "requesterEmail": "",
      "meetingType": "",
      "location": null,
      "otherDetails": "",
      "isApproved": false,
      "calendarInviteSent": false,
      "attendees": []
    },
    {
      "title": "Zain Kuwait - Rakuten Symphony",
      "purpose": "Open RAN deployment roadmap progression following initial engagement, defining Phase 2 rollout plans with Symphony orchestration for multi-vendor integration and network modernization across Kuwait operations. Network efficiency optimization and OpEx reduction strategy through AI-driven autonomous operations, plus cloud infrastructure and ecosystem partnerships to enhance digital services portfolio and drive new revenue opportunities.",
      "date": "2026-03-03",
      "startTime": "13:30",
      "endTime": "14:00",
      "sequence": 2,
      "status": "PIPELINE",
      "tags": [
        "MEA"
      ],
      "createdBy": "ts-deepa.shanker@rakuten.com",
      "requesterEmail": "shadi.sayed@rakuten.com",
      "meetingType": "Sales/Customer",
      "location": null,
      "otherDetails": "",
      "isApproved": false,
      "calendarInviteSent": false,
      "room": "Meeting Room 1 (Mickey)",
      "attendees": [
        "rsus-RS_marketing@rakuten.com",
        "sharad.sriwastawa@rakuten.com",
        "sandeep.arora@rakuten.com",
        "shadi.sayed@rakuten.com",
        "daaij.aloud@kw.zain.com",
        "nawaf.algharabally@kw.zain.com"
      ]
    },
    {
      "title": "STC - Rakuten Symphony",
      "purpose": "Vision 2030 alignment through Open RAN and autonomous network transformation, positioning STC as regional technology leader with Symphony-powered AI-driven operations and network intelligence. Strategic cloud infrastructure partnership for enterprise and consumer digital services expansion, with ecosystem collaboration opportunities in smart cities, IoT, and emerging technology ventures across Saudi Arabia and beyond.",
      "date": "2026-03-02",
      "startTime": "11:00",
      "endTime": "11:30",
      "sequence": 0,
      "status": "PIPELINE",
      "tags": [
        "MEA"
      ],
      "createdBy": "ts-deepa.shanker@rakuten.com",
      "requesterEmail": "shadi.sayed@rakuten.com",
      "meetingType": "Sales/Customer",
      "location": null,
      "otherDetails": "",
      "isApproved": false,
      "calendarInviteSent": false,
      "room": "Meeting Room 2 (Sharad)",
      "attendees": [
        "sharad.sriwastawa@rakuten.com",
        "udai.kanukolanu@rakuten.com",
        "sandeep.arora@rakuten.com",
        "shadi.sayed@rakuten.com",
        "uwetaid@stc.com.sa"
      ]
    },
    {
      "title": "Tawal - Rakuten Symphony",
      "purpose": "Open RAN in-building active infrastructure sharing model for Saudi Arabia's three MNOs (STC, Mobily, Zain), leveraging Symphony platform for multi-tenant orchestration and neutral host deployment economics. Business case development for Open RAN-based active sharing across commercial buildings, malls, and venues with focus on capex reduction, network slicing capabilities, and new revenue streams from shared infrastructure.",
      "date": "2026-03-04",
      "startTime": "09:00",
      "endTime": "09:30",
      "sequence": 0,
      "status": "PIPELINE",
      "tags": [
        "MEA"
      ],
      "createdBy": "ts-deepa.shanker@rakuten.com",
      "requesterEmail": "shadi.sayed@rakuten.com",
      "meetingType": "Sales/Customer",
      "location": null,
      "otherDetails": "",
      "isApproved": false,
      "calendarInviteSent": false,
      "room": "Meeting Room 2 (Sharad)",
      "attendees": [
        "sharad.sriwastawa@rakuten.com",
        "udai.kanukolanu@rakuten.com",
        "sandeep.arora@rakuten.com",
        "shadi.sayed@rakuten.com",
        "amoaiqel@tawal.com.sa"
      ]
    },
    {
      "title": "Ooredoo Group - Rakuten Symphony",
      "purpose": "",
      "date": "2026-03-03",
      "startTime": "16:00",
      "endTime": "16:30",
      "sequence": 0,
      "status": "PIPELINE",
      "tags": [
        "MEA"
      ],
      "createdBy": "ts-deepa.shanker@rakuten.com",
      "requesterEmail": "shadi.sayed@rakuten.com",
      "meetingType": "Sales/Customer",
      "location": null,
      "otherDetails": "",
      "isApproved": false,
      "calendarInviteSent": false,
      "room": "Meeting Room 2 (Sharad)",
      "attendees": [
        "sharad.sriwastawa@rakuten.com",
        "udai.kanukolanu@rakuten.com",
        "sandeep.arora@rakuten.com",
        "shadi.sayed@rakuten.com",
        "afakhroo@qm.org.qa"
      ]
    },
    {
      "title": "Aritel Africa- Rakuten Symphony",
      "purpose": "Open RAN economics and deployment roadmap for Africa operations, leveraging Rakuten's learnings to reduce capex/opex while improving network performance through Symphony automation. Autonomous network capabilities for operational efficiency at scale, plus cloud infrastructure partnerships to strengthen Airtel Payments Bank, digital services, and enterprise solutions ecosystem.",
      "date": "2026-03-03",
      "startTime": "15:30",
      "endTime": "16:00",
      "sequence": 0,
      "status": "PIPELINE",
      "tags": [
        "MEA"
      ],
      "createdBy": "ts-deepa.shanker@rakuten.com",
      "requesterEmail": "shadi.sayed@rakuten.com",
      "meetingType": "Sales/Customer",
      "location": null,
      "otherDetails": "",
      "isApproved": false,
      "calendarInviteSent": false,
      "room": "Meeting Room 2 (Sharad)",
      "attendees": [
        "sharad.sriwastawa@rakuten.com",
        "udai.kanukolanu@rakuten.com",
        "sandeep.arora@rakuten.com",
        "shadi.sayed@rakuten.com",
        "sunil.taldar@africa.airtel.com"
      ]
    },
    {
      "title": "Axiata - Rakuten Symphony",
      "purpose": "For RAN SMO RFP, Rakuten Symphony is a shortlisted Vendor. Axiata Group is planning to deploy in 3 OPCOs the RAN SMO with RIC capability to enhance their operation",
      "date": "2026-03-02",
      "startTime": "10:00",
      "endTime": "10:30",
      "sequence": 0,
      "status": "PIPELINE",
      "tags": [
        "APAC"
      ],
      "createdBy": "ts-deepa.shanker@rakuten.com",
      "requesterEmail": "rishi.shukla@rakuten.com",
      "meetingType": "Sales/Customer",
      "location": null,
      "otherDetails": "",
      "isApproved": false,
      "calendarInviteSent": false,
      "room": "Meeting Room 1 (Mickey)",
      "attendees": [
        "rsus-RS_marketing@rakuten.com",
        "sharad.sriwastawa@rakuten.com",
        "udai.kanukolanu@rakuten.com",
        "sandeep.arora@rakuten.com",
        "vivek@axiata.com",
        "thomas.hundt@axiata.com"
      ]
    },
    {
      "title": "Mobifone - Rakuten Symphony",
      "purpose": "We are doing a 5G POC and in discussion to expand the footprint in ORAN in Mobifone network. Objective is to strengthen the relationship and to agree on next phase",
      "date": "2026-03-03",
      "startTime": "14:30",
      "endTime": "15:00",
      "sequence": 0,
      "status": "PIPELINE",
      "tags": [
        "APAC"
      ],
      "createdBy": "ts-deepa.shanker@rakuten.com",
      "requesterEmail": "rishi.shukla@rakuten.com",
      "meetingType": "Sales/Customer",
      "location": null,
      "otherDetails": "",
      "isApproved": false,
      "calendarInviteSent": false,
      "room": "Meeting Room 2 (Sharad)",
      "attendees": [
        "sharad.sriwastawa@rakuten.com",
        "udai.kanukolanu@rakuten.com",
        "sandeep.arora@rakuten.com",
        "rishi.shukla@rakuten.com",
        "bao.vinh@mobifone.vn"
      ]
    },
    {
      "title": "BSNL - Rakuten Symphony",
      "purpose": "We are engaged with BSNL for ORAN POC and looking at expansion and strengthening the relationship in",
      "date": "2026-03-03",
      "startTime": "09:30",
      "endTime": "10:00",
      "sequence": 0,
      "status": "PIPELINE",
      "tags": [
        "APAC"
      ],
      "createdBy": "ts-deepa.shanker@rakuten.com",
      "requesterEmail": "rishi.shukla@rakuten.com",
      "meetingType": "Sales/Customer",
      "location": null,
      "otherDetails": "",
      "isApproved": false,
      "calendarInviteSent": false,
      "room": "Meeting Room 2 (Sharad)",
      "attendees": [
        "sharad.sriwastawa@rakuten.com",
        "udai.kanukolanu@rakuten.com",
        "sandeep.arora@rakuten.com",
        "rishi.shukla@rakuten.com"
      ]
    },
    {
      "title": "IOH - Rakuten Symphony",
      "purpose": "Multiple discussion on AI and Automation in multiple domains of the network. Objective is to discuss next level of partnership and Executive level connect.  ",
      "date": "2026-03-03",
      "startTime": "15:00",
      "endTime": "15:30",
      "sequence": 0,
      "status": "PIPELINE",
      "tags": [
        "APAC"
      ],
      "createdBy": "ts-deepa.shanker@rakuten.com",
      "requesterEmail": "rishi.shukla@rakuten.com",
      "meetingType": "Sales/Customer",
      "location": null,
      "otherDetails": "",
      "isApproved": false,
      "calendarInviteSent": false,
      "room": "Meeting Room 2 (Sharad)",
      "attendees": [
        "sharad.sriwastawa@rakuten.com",
        "udai.kanukolanu@rakuten.com",
        "sandeep.arora@rakuten.com",
        "rishi.shukla@rakuten.com",
        "desmond.cheung@ioh.co.id",
        "luthfi.auzan@ioh.co.id"
      ]
    },
    {
      "title": "StarHub - Rakuten Symphony",
      "purpose": "We are engaged in Network Automation discussions. We are looking at taking this to next level Strategic Partnership and Executive connect.   ",
      "date": "2026-03-04",
      "startTime": "09:30",
      "endTime": "10:00",
      "sequence": 0,
      "status": "PIPELINE",
      "tags": [
        "APAC"
      ],
      "createdBy": "ts-deepa.shanker@rakuten.com",
      "requesterEmail": "rishi.shukla@rakuten.com",
      "meetingType": "Sales/Customer",
      "location": null,
      "otherDetails": "",
      "isApproved": false,
      "calendarInviteSent": false,
      "room": "Meeting Room 2 (Sharad)",
      "attendees": [
        "nikhile@starhub.com"
      ]
    },
    {
      "title": "Singtel - Rakuten Symphony",
      "purpose": "We are engaged in multiple RFPs for network automation. In discussion for POC. We are looking at taking this to next level Strategic Partnership and Executive connect.  ",
      "date": "2026-03-04",
      "startTime": "10:00",
      "endTime": "10:30",
      "sequence": 0,
      "status": "PIPELINE",
      "tags": [
        "APAC"
      ],
      "createdBy": "ts-deepa.shanker@rakuten.com",
      "requesterEmail": "",
      "meetingType": "Sales/Customer",
      "location": null,
      "otherDetails": "",
      "isApproved": false,
      "calendarInviteSent": false,
      "room": "Meeting Room 2 (Sharad)",
      "attendees": [
        "sharad.sriwastawa@rakuten.com",
        "udai.kanukolanu@rakuten.com",
        "sandeep.arora@rakuten.com",
        "rishi.shukla@rakuten.com",
        "kmyuen@singtel.com",
        "jorge.fernandes@singtel.com"
      ]
    },
    {
      "title": "MTN Group - Rakuten  ",
      "purpose": "PURPOSE:\nExecutive trust and relationship established\nCommitment to Tokyo HQ visit confirmed\n 90-day acceleration plan agreed\nStrategic partnership discussions initiated\nClear differentiation from vendor relationships\nAGENDA\n1. Welcome & Context\n2. Rakuten Group\n3. Rakuten Mobile & Symphony\n4. MTN Group's Strategic Vision & Priorities\n5. Strategic Partnership Framework & Next Steps",
      "date": "2026-03-03",
      "startTime": "11:30",
      "endTime": "12:00",
      "sequence": 2,
      "status": "PIPELINE",
      "tags": [
        "MEA"
      ],
      "createdBy": "ts-deepa.shanker@rakuten.com",
      "requesterEmail": "shadi.sayed@rakuten.com",
      "meetingType": "Sales/Customer",
      "location": null,
      "otherDetails": "",
      "isApproved": false,
      "calendarInviteSent": false,
      "room": "Meeting Room 1 (Mickey)",
      "attendees": [
        "rsus-RS_marketing@rakuten.com",
        "sharad.sriwastawa@rakuten.com",
        "udai.kanukolanu@rakuten.com",
        "faiq.khan@rakuten.com",
        "sandeep.arora@rakuten.com",
        "shadi.sayed@rakuten.com",
        "Ralph.Mupita@mtn.com"
      ]
    },
    {
      "title": "Axiata Digital Lab - Rakuten Symphony",
      "purpose": "For RAN SMO RFP, Rakuten Symphony is a shortlisted Vendor. ADL is our partner which is Axiata Subsidiary. Axiata CIO and VP Strategy intend to discuss broader alliance with Rakuten Symphony on Automation, AI capability development.",
      "date": "2026-03-03",
      "startTime": "13:00",
      "endTime": "13:30",
      "sequence": 1,
      "status": "PIPELINE",
      "tags": [
        "APAC"
      ],
      "createdBy": "ts-deepa.shanker@rakuten.com",
      "requesterEmail": "rishi.shukla@rakuten.com",
      "meetingType": "Sales/Customer",
      "location": null,
      "otherDetails": "",
      "isApproved": false,
      "calendarInviteSent": false,
      "room": "Meeting Room 2 (Sharad)",
      "attendees": [
        "sharad.sriwastawa@rakuten.com",
        "udai.kanukolanu@rakuten.com",
        "vivek.murthy@rakuten.com",
        "sandeep.arora@rakuten.com",
        "rishi.shukla@rakuten.com",
        "tomek@axiata.com",
        "anthony.rodrigo@axiata.com"
      ]
    },
    {
      "title": "Grameenphone -  Rakuten Symphony",
      "purpose": "We are doing 5G POC. Discussion around 5G expansion once the Government issue 5G licenses. ",
      "date": "2026-03-03",
      "startTime": "14:00",
      "endTime": "14:30",
      "sequence": 0,
      "status": "PIPELINE",
      "tags": [
        "APAC"
      ],
      "createdBy": "ts-deepa.shanker@rakuten.com",
      "requesterEmail": "rishi.shukla@rakuten.com",
      "meetingType": "Sales/Customer",
      "location": null,
      "otherDetails": "",
      "isApproved": false,
      "calendarInviteSent": false,
      "room": "Meeting Room 2 (Sharad)",
      "attendees": [
        "sharad.sriwastawa@rakuten.com",
        "udai.kanukolanu@rakuten.com",
        "sandeep.arora@rakuten.com",
        "rishi.shukla@rakuten.com",
        "jai.prakash@grameenphone.com",
        "abshibly@grameenphone.com"
      ]
    },
    {
      "title": "Airtel - Rakuten Symphony",
      "purpose": "Multiple engagements are taking place related to Automation, AI site analytics, and small cells. The objective is to strengthen our relationship and future engagement.  ",
      "date": "2026-03-02",
      "startTime": "13:30",
      "endTime": "14:00",
      "sequence": 1,
      "status": "PIPELINE",
      "tags": [
        "APAC"
      ],
      "createdBy": "ts-deepa.shanker@rakuten.com",
      "requesterEmail": "rishi.shukla@rakuten.com",
      "meetingType": "Sales/Customer",
      "location": null,
      "otherDetails": "",
      "isApproved": false,
      "calendarInviteSent": false,
      "room": "Meeting Room 1 (Mickey)",
      "attendees": [
        "rsus-RS_marketing@rakuten.com",
        "sharad.sriwastawa@rakuten.com",
        "udai.kanukolanu@rakuten.com",
        "sandeep.arora@rakuten.com",
        "rishi.shukla@rakuten.com",
        "shashwat.sharma@airtel.com"
      ]
    },
    {
      "title": "Xplore x Rakuten Symphony",
      "purpose": "TBD",
      "date": "2026-03-03",
      "startTime": "09:00",
      "endTime": "09:30",
      "sequence": 1,
      "status": "PIPELINE",
      "tags": [
        "Americas"
      ],
      "createdBy": "jessica.cheng@rakuten.com",
      "requesterEmail": "sachin.mahajan@rakuten.com",
      "meetingType": "Sales/Customer",
      "location": null,
      "otherDetails": "Rakuten Symphony has been working closely with the Xplore team across a couple of initiatives spanning Open RAN and OSS. ",
      "isApproved": false,
      "calendarInviteSent": false,
      "room": "Meeting Room 1 (Mickey)",
      "attendees": [
        "rsus-RS_marketing@rakuten.com",
        "sharad.sriwastawa@rakuten.com",
        "udai.kanukolanu@rakuten.com",
        "sachin.mahajan@rakuten.com",
        "richard.thalluri@rakuten.com"
      ]
    }
  ]
}